perseus/__init__.py
perseus/__main__.py
perseus/cli.py
perseus-0.1.1.dist-info/entry_points.txt
perseus-0.1.1.dist-info/LICENSE
perseus-0.1.1.dist-info/WHEEL
perseus-0.1.1.dist-info/METADATA
perseus-0.1.1.dist-info/RECORD
