Metadata-Version: 2.1
Name: perseus
Version: 0.1.1
Summary: Snapshot management tool
Home-page: https://github.com/b0g3r/perseus
License: MIT
Author: Boger
Author-email: kotvberloge@gmail.com
Requires-Python: >=3.7,<4.0
Classifier: License :: OSI Approved :: MIT License
Classifier: Programming Language :: Python :: 3
Classifier: Programming Language :: Python :: 3.7
Classifier: Programming Language :: Python :: 3.8
Project-URL: Repository, https://github.com/b0g3r/perseus
